README.rst
setup.py
fesol/__init__.py
fesol/_version.py
fesol/common.py
fesol/heat.py
fesol/interface.py
fesol.egg-info/PKG-INFO
fesol.egg-info/SOURCES.txt
fesol.egg-info/dependency_links.txt
fesol.egg-info/requires.txt
fesol.egg-info/top_level.txt