Metadata-Version: 1.1
Name: fesol
Version: 0.1.1
Summary: Simple Finite Element Solvers
Home-page: https://bitbucket.org/QiaoC/fesol
Author: Qiao Chen
Author-email: qiao.chen@stonybrook.edu
License: MIT
Keywords: Math
Platform: UNKNOWN
Classifier: Programming Language :: Python :: 3.5
Classifier: Topic :: Scientific/Engineering
Classifier: Topic :: Software Development
Classifier: Operating System :: POSIX :: Linux
Classifier: Intended Audience :: Science/Research
